setup.py
mead/__init__.py
mead/context.py
mead/exceptions.py
mead/objects.py
mead/response.py
mead/router.py
mead/server.py
mead.egg-info/PKG-INFO
mead.egg-info/SOURCES.txt
mead.egg-info/dependency_links.txt
mead.egg-info/requires.txt
mead.egg-info/top_level.txt