Metadata-Version: 1.0
Name: mead
Version: 0.0.11
Summary: Flexible aiohttp Web Framework
Home-page: UNKNOWN
Author: minamorl
Author-email: minamorl@minamorl.com
License: UNKNOWN
Platform: UNKNOWN
